[
  {
    "date": "2024-11-15",
    "stopName": "Sunshine Daycare Center",
    "stopType": "daycare",
    "stopAddress": "123 Elm Street",
    "stopZipCode": "19123",
    "booksDistributed": 75,
    "contactMethod": "Phone call",
    "howHeardAboutUs": "Word of mouth",
    "didWeReadToThem": true,
    "daycareSettings": { "hasStickerDisplayed": true },
    "branchSettings": { "hasSignageDisplayed": false },
    "communityEventSettings": { "wereWeOnFlyer": false, "featuredOnTheirSocialMedia": false, "didWeShareOnOurSocialMedia": false },
    "notes": "Great visit! Kids loved the story time."
  },
  {
    "date": "2024-11-18",
    "stopName": "Kensington Branch Library",
    "stopType": "branch",
    "stopAddress": "456 Frankford Avenue",
    "stopZipCode": "19125",
    "booksDistributed": 120,
    "contactMethod": "Email",
    "howHeardAboutUs": "Library partnership",
    "didWeReadToThem": true,
    "daycareSettings": { "hasStickerDisplayed": false },
    "branchSettings": { "hasSignageDisplayed": true },
    "communityEventSettings": { "wereWeOnFlyer": false, "featuredOnTheirSocialMedia": false, "didWeShareOnOurSocialMedia": false },
    "notes": "Regular monthly stop. Good turnout."
  },
  {
    "date": "2024-11-22",
    "stopName": "Fall Festival at Clark Park",
    "stopType": "community_event",
    "stopAddress": "4300 Baltimore Avenue",
    "stopZipCode": "19104",
    "booksDistributed": 250,
    "contactMethod": "Partner organization referral",
    "howHeardAboutUs": "Previous event collaboration",
    "didWeReadToThem": false,
    "daycareSettings": { "hasStickerDisplayed": false },
    "branchSettings": { "hasSignageDisplayed": false },
    "communityEventSettings": { "wereWeOnFlyer": true, "featuredOnTheirSocialMedia": true, "didWeShareOnOurSocialMedia": true },
    "notes": "Huge event! Many families. Need more volunteers next time."
  },
  {
    "date": "2024-12-02",
    "stopName": "Little Stars Learning Center",
    "stopType": "daycare",
    "stopAddress": "789 Market Street",
    "stopZipCode": "19107",
    "booksDistributed": 45,
    "contactMethod": "Website form",
    "howHeardAboutUs": "Google search",
    "didWeReadToThem": true,
    "daycareSettings": { "hasStickerDisplayed": false },
    "branchSettings": { "hasSignageDisplayed": false },
    "communityEventSettings": { "wereWeOnFlyer": false, "featuredOnTheirSocialMedia": false, "didWeShareOnOurSocialMedia": false },
    "notes": "First visit. They want to become a regular stop."
  },
  {
    "date": "2024-12-05",
    "stopName": "North Philly Community Center",
    "stopType": "branch",
    "stopAddress": "2100 N Broad Street",
    "stopZipCode": "19121",
    "booksDistributed": 85,
    "contactMethod": "Phone call",
    "howHeardAboutUs": "Community board",
    "didWeReadToThem": true,
    "daycareSettings": { "hasStickerDisplayed": false },
    "branchSettings": { "hasSignageDisplayed": true },
    "communityEventSettings": { "wereWeOnFlyer": false, "featuredOnTheirSocialMedia": false, "didWeShareOnOurSocialMedia": false },
    "notes": "After-school program kids. Very engaged."
  },
  {
    "date": "2024-12-10",
    "stopName": "Holiday Market at Reading Terminal",
    "stopType": "community_event",
    "stopAddress": "51 N 12th Street",
    "stopZipCode": "19107",
    "booksDistributed": 180,
    "contactMethod": "Email from event organizer",
    "howHeardAboutUs": "City partnership program",
    "didWeReadToThem": false,
    "daycareSettings": { "hasStickerDisplayed": false },
    "branchSettings": { "hasSignageDisplayed": false },
    "communityEventSettings": { "wereWeOnFlyer": true, "featuredOnTheirSocialMedia": false, "didWeShareOnOurSocialMedia": true },
    "notes": "Holiday-themed books were a hit!"
  },
  {
    "date": "2024-12-12",
    "stopName": "Tiny Tots Academy",
    "stopType": "daycare",
    "stopAddress": "333 South Street",
    "stopZipCode": "19147",
    "booksDistributed": 60,
    "contactMethod": "Referral from Sunshine Daycare",
    "howHeardAboutUs": "Another daycare",
    "didWeReadToThem": true,
    "daycareSettings": { "hasStickerDisplayed": true },
    "branchSettings": { "hasSignageDisplayed": false },
    "communityEventSettings": { "wereWeOnFlyer": false, "featuredOnTheirSocialMedia": false, "didWeShareOnOurSocialMedia": false },
    "notes": "Small but enthusiastic group. Requested monthly visits."
  },
  {
    "date": "2024-12-14",
    "stopName": "West Philly Winter Wonderland",
    "stopType": "community_event",
    "stopAddress": "5100 Walnut Street",
    "stopZipCode": "19139",
    "booksDistributed": 200,
    "contactMethod": "Community leader outreach",
    "howHeardAboutUs": "Social media",
    "didWeReadToThem": true,
    "daycareSettings": { "hasStickerDisplayed": false },
    "branchSettings": { "hasSignageDisplayed": false },
    "communityEventSettings": { "wereWeOnFlyer": true, "featuredOnTheirSocialMedia": true, "didWeShareOnOurSocialMedia": true },
    "notes": "Great turnout despite cold weather. Hot cocoa helped!"
  }
]
